biomarker/__init__.py
biomarker/main.py
biomarker/modules/__init__.py
biomarker/static/Dockerfile
biomarker/static/env.yaml
biomarker/utils/__init__.py
biomarker-0.1.0.dist-info/METADATA
biomarker-0.1.0.dist-info/WHEEL
biomarker-0.1.0.dist-info/RECORD
